playdice/__init__.py
playdice/playdice.py
playdice-2025.7.26.0.dist-info/METADATA
playdice-2025.7.26.0.dist-info/WHEEL
playdice-2025.7.26.0.dist-info/entry_points.txt
playdice-2025.7.26.0.dist-info/top_level.txt
playdice-2025.7.26.0.dist-info/RECORD
