Metadata-Version: 2.4
Name: playdice
Version: 2025.7.26.0
Summary: Simplistically play dice
Author-email: Ann T Ropea <bedhanger@gmx.de>
License-Expression: MIT
Project-URL: Homepage, https://gitlab.com/bedhanger/mwe/-/tree/master/python/playdice
Provides-Extra: colour
Requires-Dist: termcolor; extra == "colour"
Provides-Extra: test
Requires-Dist: pytest; extra == "test"
